pyexcel_export/__init__.py
pyexcel_export/app.py
pyexcel_export/defaults.py
pyexcel_export/formatter.py
pyexcel_export/serialize.py
pyexcel_export/yaml_serialize.py
pyexcel_export-0.3.6.dist-info/LICENSE
pyexcel_export-0.3.6.dist-info/WHEEL
pyexcel_export-0.3.6.dist-info/METADATA
pyexcel_export-0.3.6.dist-info/RECORD
