Metadata-Version: 2.1
Name: pyexcel-export
Version: 0.3.6
Summary: Keep good formatting when exporting to *.xlsx, *.yaml and *.json and when updating data.
Home-page: https://github.com/patarapolw/pyexcel-export
License: MIT
Keywords: excel,openpyxl,pyexcel,yaml
Author: Pacharapol Withayasakpunt
Author-email: patarapolw@gmail.com
Requires-Python: >=3.5
Classifier: License :: OSI Approved :: MIT License
Classifier: Programming Language :: Python :: 3
Classifier: Programming Language :: Python :: 3.5
Classifier: Programming Language :: Python :: 3.6
Classifier: Programming Language :: Python :: 3.7
Classifier: Programming Language :: Python :: 3.8
Requires-Dist: openpyxl (>=2.5.0,<2.6.0)
Requires-Dist: oyaml (>=0.5.0,<0.6.0)
Requires-Dist: pyexcel (>=0.5.8,<0.6.0)
Project-URL: Repository, https://github.com/patarapolw/pyexcel-export
